taygete/__init__.py
taygete/__main__.py
taygete/configure.py
taygete/tests/__init__.py
taygete/tests/test_init.py
taygete-2024.1.12.1657.dist-info/METADATA
taygete-2024.1.12.1657.dist-info/WHEEL
taygete-2024.1.12.1657.dist-info/top_level.txt
taygete-2024.1.12.1657.dist-info/RECORD
