Metadata-Version: 2.1
Name: taygete
Version: 2024.1.12.1657
Summary: A moon of Jupiter in the Carme group
Author-email: Moshe Zadka <moshez@zadka.club>
License: Permission is hereby granted, free of charge, to any person obtaining a
Project-URL: Homepage, https://github.com/carme-group/taygete
Requires-Python: >=3.11
Requires-Dist: ncolony
Requires-Dist: pycus
Requires-Dist: jupyterlab
Requires-Dist: virtualenvwrapper
Requires-Dist: httpx
Requires-Dist: ipywidgets
Requires-Dist: pipx
Provides-Extra: docs
Requires-Dist: sphinx ; extra == 'docs'
Provides-Extra: lint
Requires-Dist: flake8 ; extra == 'lint'
Requires-Dist: black ; extra == 'lint'
Provides-Extra: mypy
Requires-Dist: mypy ; extra == 'mypy'
Provides-Extra: tests
Requires-Dist: virtue ; extra == 'tests'
Requires-Dist: pyhamcrest ; extra == 'tests'
Requires-Dist: coverage ; extra == 'tests'
